{
  "ldr_scan_dict": {
    "l1": {
      "range": 150,
      "resolution": 5
    },
    "l2": {
      "range": 150,
      "resolution": 5
    },
    "l3": {
      "range": 150,
      "resolution": 5
    },
    "g1": {
      "range": 150,
      "resolution": 5
    },
    "g2": {
      "range": 150,
      "resolution": 5
    }
  },
  "hard_limits": {
    "laser_wavelength": [
      650,
      1000
    ],
    "monochromator_wavelength": [
      500,
      1300
    ]
  },
  "home_positions": {
    "1A": 0,
    "1X": -110749,
    "1Y": -14107,
    "1Z": -40306,
    "2A": 0,
    "2X": 0,
    "2Y": 0,
    "2Z": 0,
    "3A": -15047,
    "3X": -17054,
    "3Y": -17723,
    "3Z": -13056,
    "4A": 0,
    "4X": 0,
    "4Y": 0,
    "4Z": 0
  },
  "last_stage_position": {
    "X": 0,
    "Y": 0,
    "Z": 0,
    "A": 0
  },
  "action_groups": {
    "laser_wavelength": {
      "l1": "1X",
      "l2": "1Y",
      "l3": "1Z"
    },
    "monochromator_wavelength": {
      "g1": "3X",
      "g2": "3Y",
      "g3": "3Z",
      "g4": "3A"
    },
    "polarization": {
      "in": "4X",
      "out": "4Y"
    },
    "triax": {
      "triax": "triax"
    },
    "stage_movement": {
      "X": "2X",
      "Y": "2Y",
      "Z": "2Z",
      "mode": "2A"
    }
  }
}